tradedesk_dukascopy/__init__.py
tradedesk_dukascopy/cli.py
tradedesk_dukascopy/export.py
tradedesk_dukascopy/metadata.py
tradedesk_dukascopy/parallel.py
tradedesk_dukascopy-0.1.2.dist-info/METADATA
tradedesk_dukascopy-0.1.2.dist-info/WHEEL
tradedesk_dukascopy-0.1.2.dist-info/entry_points.txt
tradedesk_dukascopy-0.1.2.dist-info/licenses/LICENSE
tradedesk_dukascopy-0.1.2.dist-info/RECORD
