Metadata-Version: 2.4
Name: tradedesk-dukascopy
Version: 0.1.2
Summary: Dukascopy tick downloader and candle/tick exporter for backtesting workflows.
Project-URL: Homepage, https://github.com/radiusred
Project-URL: Repository, https://github.com/radiusred/tradedesk-dukascopy
Project-URL: Issues, https://github.com/radiusred/tradedesk-dukascopy/issues
Author-email: "Radius Red Ltd." <opensource@radiusred.uk>
Maintainer-email: "Radius Red Ltd." <opensource@radiusred.uk>
License-Expression: Apache-2.0
License-File: LICENSE
Keywords: backtesting,candles,dukascopy,ticks,trading
Classifier: Operating System :: OS Independent
Classifier: Programming Language :: Python :: 3
Requires-Python: >=3.11
Requires-Dist: pandas>=2.2
Requires-Dist: requests>=2.32
Requires-Dist: rich>=14.2
Provides-Extra: dev
Requires-Dist: mypy>=1.19; extra == 'dev'
Requires-Dist: pandas-stubs>=2.2.0; extra == 'dev'
Requires-Dist: pre-commit>=4.5; extra == 'dev'
Requires-Dist: pytest-cov>=7.0; extra == 'dev'
Requires-Dist: pytest>=9.0; extra == 'dev'
Requires-Dist: ruff>=0.14; extra == 'dev'
Requires-Dist: types-requests>=2.32.0; extra == 'dev'
Provides-Extra: parquet
Requires-Dist: pyarrow>=16.1; extra == 'parquet'
